library1_xjl/library.py
library1_xjl-1.0.0.dist-info/LICENSE
library1_xjl-1.0.0.dist-info/METADATA
library1_xjl-1.0.0.dist-info/WHEEL
library1_xjl-1.0.0.dist-info/top_level.txt
library1_xjl-1.0.0.dist-info/RECORD
