Metadata-Version: 2.1
Name: library1-xjl
Version: 1.0.0
Summary: homework1 library
Home-page: UNKNOWN
Author: Junlu Xu
Author-email: jx2211@nyu.edu
License: MIT LICENSE
Platform: all
Classifier: Intended Audience :: Developers
Classifier: Operating System :: OS Independent
Classifier: Natural Language :: English
Classifier: Programming Language :: Python
Classifier: Programming Language :: Python :: 2
Classifier: Programming Language :: Python :: 2.7
Classifier: Programming Language :: Python :: 3
Classifier: Programming Language :: Python :: 3.5
Classifier: Programming Language :: Python :: 3.6
Classifier: Programming Language :: Python :: 3.7
Classifier: Programming Language :: Python :: 3.8
Classifier: Topic :: Software Development :: Libraries
License-File: LICENSE
